paga_connect_client/__init__.py
paga_connect_client/apibase.py
paga_connect_client/paga_connect_client_core.py
paga_connect_client/version.py
pagaconnect-0.0.2.dist-info/METADATA
pagaconnect-0.0.2.dist-info/WHEEL
pagaconnect-0.0.2.dist-info/top_level.txt
pagaconnect-0.0.2.dist-info/RECORD
