Metadata-Version: 2.1
Name: pagaconnect
Version: 0.0.2
Summary: Paga Connect Library
Home-page: https://github.com/pagadevcomm/paga-connect-python.git
Author: pagaDevComm
Author-email: devcomm@paga.com
License: UNKNOWN
Platform: UNKNOWN
Classifier: Programming Language :: Python :: 3
Classifier: Programming Language :: Python :: 3.6
Classifier: Programming Language :: Python :: 3.7
Classifier: License :: OSI Approved :: GNU General Public License v2 or later (GPLv2+)
Classifier: Operating System :: OS Independent
Requires-Dist: requests
